{
  "_id": "aeoC118-1-3",
  "formName": "C118-1-3 Business customs matters",
  "description": "",
  "emailTemplateId": "eeitt_submission_confirmation",
  "authConfig": {
    "authModule": "hmrc"
  },
  "dmsSubmission": {
    "businessArea": "For example: FinanceOpsCorpT",
    "classificationType": "For example: BT-NRU-Environmental",
    "customerId": "${fieldIdOfCustomerIdentifier}",
    "dmsFormId": "aeoC118-1-3"
  },
  "sections": [
    {
      "title": "Trader identification number(s)",
      "shortName": "Identification number(s)",
      "fields": [
        {
          "id": "eoriInfo",
          "type": "info",
          "label": "",
          "infoText": "Your trader identification number is the same as your Economic Operator Registration and Identification (EORI) number",
          "infoType": "noformat"
        },
        {
          "id": "generatedId_b05f7c22-6eb2-4c7c-a9f8-2b0c55159c29",
          "type": "info",
          "label": "Why am I being asked for this?",
          "infoText": "We use your EORI number to link together all 7 forms for your application",
          "infoType": "long"
        },
        {
          "id": "eoriGroup",
          "type": "group",
          "label": "EORI Number",
          "format": "horizontal",
          "presentationHint": "summariseGroupAsGrid",
          "fields": [
            {
              "id": "mSInfo1",
              "type": "info",
              "label": "Member states country codes",
              "infoText": "Find the required [member state country codes](https://www.gov.uk/government/publications/uk-trade-tariff-country-and-currency-codes/uk-trade-tariff-country-and-currency-codes#a \"Member state country codes\") here \n\n You will need to press back in your browser to get back to this form ",
              "infoType": "long"
            },
            {
              "id": "eORIa",
              "type": "text",
              "label": "",
              "helpText": "Enter your country code, for example GB, followed by your 12 numerical digit EORI number",
              "format": "text(14,17)",
              "mandatory": "true",
              "errorMessage": "Input your country code and EORI number"
            }
          ]
        }
      ]
    },
    {
      "title": "Information and statistics on customs matters (1.3.1)",
      "shortName": "Information and statistics (1.3.1)",
      "fields": [
        {
          "id": "stats1",
          "type": "choice",
          "label": "Do you perform customs formalities in your own name and for your own account? ",
          "shortName": "Perform own custom formalities (1.3.1a)",
          "format": "yesno"
        }
      ]
    },
    {
      "title": "Information and statistics on customs matters",
      "shortName": "Personal representative",
      "fields": [
        {
          "id": "stats2",
          "type": "choice",
          "label": "Is someone representing you regarding customs formalities?",
          "shortName": "Represented by someone else (1.3.1b) ",
          "format": "yesno"
        }
      ]
    },
    {
      "title": "Information and statistics on customs matters",
      "shortName": "Your representative",
      "includeIf": "${stats2 = 0}",
      "fields": [
        {
          "id": "stats2b",
          "type": "info",
          "label": "",
          "infoText": "If 'Yes', by whom and how (directly or indirectly)?\n\n Include the name, address and EORI number of the representative",
          "infoType": "noformat"
        },
        {
          "id": "stats2a",
          "type": "text",
          "label": "",
          "shortName": "Person representing you",
          "multiline": "yes"
        }
      ]
    },
    {
      "title": "Information and statistics on customs matters",
      "shortName": "People you represent",
      "fields": [
        {
          "id": "stats3",
          "type": "choice",
          "label": "Do you represent other persons in customs formalities?",
          "shortName": "Represent others (1.3.1c)",
          "format": "yesno"
        }
      ]
    },
    {
      "title": "Who do you represent?",
      "shortName": "People represented",
      "includeIf": "${stats3 = 0}",
      "fields": [
        {
          "id": "stats3b",
          "type": "info",
          "label": "",
          "infoText": "Who do you represent (Name the most significant clients)?\n\n How do you represent them (directly or indirectly)?",
          "infoType": "noformat"
        },
        {
          "id": "stats3a",
          "type": "text",
          "label": "",
          "shortName": "People you represent",
          "multiline": "yes"
        }
      ]
    },
    {
      "title": "Tariff classification of goods",
      "shortName": "Tariff classification (1.3.2)",
      "fields": [
        {
          "id": "tariffLong1",
          "type": "text",
          "label": "How, and by whom, is the tariff classification of goods decided? ",
          "shortName": "How classification is decided (1.3.2a)",
          "multiline": "yes"
        }
      ]
    },
    {
      "title": "Tariff classification of goods",
      "shortName": "Tariff classification quality assurance",
      "fields": [
        {
          "id": "tariffLong2",
          "type": "text",
          "label": "What quality assurance measures do you take to make sure that tariff classifications are correct (for example, checks, plausibility checks, internal working instructions, regular training)? ",
          "shortName": "Quality assurance measures (1.3.2b)",
          "multiline": "yes"
        }
      ]
    },
    {
      "title": "Tariff classification of goods",
      "shortName": "Quality assurance notes",
      "fields": [
        {
          "id": "qANotes2",
          "type": "choice",
          "label": "Do you keep notes on these quality assurance measures?",
          "shortName": "Notes kept on quality assurance measures (1.3.2c)",
          "format": "yesno"
        },
        {
          "id": "qANotes3",
          "type": "choice",
          "label": "Do you regularly monitor the effectiveness of your quality assurance measures?",
          "shortName": "effectiveness monitored (1.3.2d)",
          "format": "yesno"
        }
      ]
    },
    {
      "title": "Tariff classification of goods",
      "shortName": "Tariff classification resources used",
      "fields": [
        {
          "id": "tariffLong3",
          "type": "text",
          "label": "What resources do you use for tariff classification (for example, database of standing data on goods)?",
          "shortName": "Tariff classification resources (1.3.2e)",
          "multiline": "yes"
        }
      ]
    },
    {
      "title": "Customs value (1.3.3)",
      "shortName": "Customs value (1.3.3)",
      "fields": [
        {
          "id": "customsValue1",
          "type": "text",
          "label": "How and by whom is the customs value established?",
          "shortName": "How and by whom, the customs value is established (1.3.3a)",
          "multiline": "yes"
        }
      ]
    },
    {
      "title": "Customs value quality assurance",
      "shortName": "Customs value quality assurance",
      "fields": [
        {
          "id": "customsValue2",
          "type": "text",
          "label": "What quality assurance measures do you take to make sure that the customs value is correctly established (for example, checks, plausibility checks, internal working instructions, regular training, other means)?",
          "shortName": "Quality assurance measures (1.3.3b)",
          "multiline": "yes"
        }
      ]
    },
    {
      "title": "Customs value quality assurance",
      "shortName": "Customs value quality assurance notes",
      "fields": [
        {
          "id": "qANotes5",
          "type": "choice",
          "label": "Do you regularly monitor the effectiveness of your quality assurance measures?",
          "shortName": "effectiveness monitored (1.3.3c)",
          "format": "yesno"
        },
        {
          "id": "qANotes4",
          "type": "choice",
          "label": "Do you keep notes on these quality assurance measures?",
          "shortName": "Notes on quality assurance measures kept (1.3.3d)",
          "format": "yesno"
        }
      ]
    },
    {
      "title": "Origin of imported goods",
      "shortName": "Imported goods origins",
      "fields": [
        {
          "id": "origins1",
          "type": "text",
          "label": "Give an overview of the preferential or non-preferential origin of the imported goods. If none, state N/A",
          "shortName": "Overview of imported goods (1.3.4a)",
          "multiline": "yes"
        }
      ]
    },
    {
      "title": "Origin of imported goods internal actions",
      "shortName": "Imported goods origins internal actions",
      "fields": [
        {
          "id": "origins2",
          "type": "text",
          "label": "What internal actions have you implemented to verify that the country of origin of the imported goods is declared correctly? If none, state N/A",
          "shortName": "Internal actions implemented (1.3.4b)",
          "multiline": "yes"
        }
      ]
    },
    {
      "title": "Origin of imported goods issuing of proof",
      "shortName": "Imported goods issuing of proofs of origins",
      "fields": [
        {
          "id": "origins3",
          "type": "text",
          "label": "Describe your approach in the issuing of proof of preferences and certificates of origin for exportation. If none, state N/A",
          "shortName": "Issuing of proof (1.3.4c)",
          "multiline": "yes"
        }
      ]
    },
    {
      "title": "Goods subject to anti-dumping duties or countervailing duties?",
      "shortName": "Anti-dumping duties or countervailing duties (1.3.5)",
      "fields": [
        {
          "id": "origins5",
          "type": "choice",
          "label": "Do you deal in goods subject to anti-dumping duties or countervailing duties?",
          "format": "yesno"
        }
      ]
    },
    {
      "title": "Goods subject to anti-dumping duties or countervailing duties?",
      "shortName": "Anti-dumping duties or countervailing duties details",
      "includeIf": "${origins5 = 0}",
      "fields": [
        {
          "id": "origins6",
          "type": "text",
          "label": "Provide details of the manufacturer(s) or countries outside the EU whose goods are subject to anti-dumping duties or countervailing duties",
          "shortName": "Details of anti-dumping or countervailing duties",
          "multiline": "yes"
        }
      ]
    }
  ],
  "declarationSection": {
    "title": "Declaration",
    "shortName": "Declaration",
    "fields": [
      {
        "id": "decText",
        "type": "info",
        "label": "",
        "infoText": "Lorem ipsum dolor sit amet, consectetur adipiscing elit. Morbi sed placerat est. Integer in porttitor enim. Etiam felis sapien, eleifend eget tellus vel, pulvinar ultrices elit. Fusce at neque sit amet nibh maximus tincidunt ac ut eros. Pellentesque leo dui, mattis pulvinar turpis eu, viverra dictum lacus. Cras egestas fringilla tincidunt. Morbi interdum fermentum felis vitae elementum. In venenatis euismod efficitur. Morbi posuere auctor imperdiet. Ut et lacus rhoncus, malesuada mi sollicitudin, sagittis tellus."
      },
      {
        "id": "declarationNameGroup",
        "type": "group",
        "label": "Provide details below of who is signing the declaration",
        "fields": [
          {
            "id": "declaration-firstname",
            "type": "text",
            "label": "First name",
            "errorMessage": "First name can only include letters a to z, numbers, spaces, hyphens and apostrophes"
          },
          {
            "id": "declaration-lastname",
            "type": "text",
            "label": "Last name",
            "errorMessage": "Last name can only include letters a to z, numbers, spaces, hyphens and apostrophes"
          },
          {
            "id": "declaration-status",
            "type": "text",
            "label": "Status",
            "helpText": "For example, director, financial controller or secretary",
            "errorMessage": "Position in the company can only include letters, numbers, spaces, hyphens and apostrophes"
          }
        ]
      },
      {
        "id": "declarationEmailGroup",
        "type": "group",
        "label": "To receive confirmation that your return has been submitted, enter an email address below",
        "fields": [
          {
            "id": "email",
            "type": "text",
            "label": "Email address",
            "format": "email",
            "mandatory": "true",
            "errorMessage": "Enter a valid email address with no spaces, like name@example.com"
          }
        ]
      }
    ]
  },
  "acknowledgementSection": {
    "title": "Confirmation page",
    "shortName": "Acknowledgement Page",
    "fields": [
      {
        "id": "helpText8",
        "type": "info",
        "label": "",
        "infoText": "This is your last opportunity to print or save a pdf copy of your submitted form."
      },
      {
        "id": "ackpageInfo",
        "type": "info",
        "label": "Payment",
        "infoText": ""
      }
    ]
  },
  "submitErrorUrl": "deprecated",
  "submitSuccessUrl": "deprecated"
}